baz/__init__.py
baz/baz.py
baz/baz_args.py
baz/bazel_helpers.py
baz/bazel_prober.py
baz/constants.py
baz/filesystem.py
baz/inventory.py
baz/tui.py
baz/tests/__init__.py
baz/tests/test_command_line.py
baz-0.2.6.data/scripts/baz
baz-0.2.6.dist-info/LICENSE
baz-0.2.6.dist-info/METADATA
baz-0.2.6.dist-info/WHEEL
baz-0.2.6.dist-info/top_level.txt
baz-0.2.6.dist-info/RECORD
