Metadata-Version: 2.1
Name: baz
Version: 0.2.6
Summary: A wrapper for the Bazel build system that provides a curses GUI for persistent configuration.
Home-page: https://github.com/d3vnu1l/baz
Author: Ryan Deushane
Author-email: radeushane@gmail.com
License: UNKNOWN
Platform: UNKNOWN
Classifier: Programming Language :: Python :: 3
Classifier: License :: OSI Approved :: MIT License
Classifier: Operating System :: OS Independent
Requires-Python: >=3.5
Requires-Dist: asciimatics (>=1.11.0)
Requires-Dist: dataclasses (>=0.6)
